pygar/__init__.py
pygar/cache.py
pygar/config.py
pygar/document.py
pygar/parser.py
pygar/parser_dummy.py
pygar/parser_form.py
pygar/parser_index.py
pygar/query.py
pygar/query_csv.py
pygar/query_form.py
pygar/query_json.py
pygar/query_master.py
pygar/query_output.py
pygar/query_scrape.py
pygar/query_single_master.py
pygar-1.0.5.dist-info/LICENSE.txt
pygar-1.0.5.dist-info/METADATA
pygar-1.0.5.dist-info/RECORD
pygar-1.0.5.dist-info/WHEEL
pygar-1.0.5.dist-info/top_level.txt
