Metadata-Version: 2.1
Name: pygar
Version: 1.0.5
Summary: Searches the SEC's Edgar database using a variety of methods
Home-page: https://bcable.net/x/pygaR
Author: Brad Cable
Author-email: brad@bcable.net
License: MIT
Keywords: pygar edgar sec stock filing
Platform: UNKNOWN
Classifier: Development Status :: 5 - Production/Stable
Classifier: Intended Audience :: Science/Research
Classifier: Topic :: Office/Business :: Financial :: Investment
Classifier: Topic :: Scientific/Engineering :: Information Analysis
Classifier: License :: OSI Approved :: MIT License
Classifier: Programming Language :: Python :: 2
Classifier: Programming Language :: Python :: 2.7
Classifier: Programming Language :: Python :: 3
Classifier: Programming Language :: Python :: 3.3
Classifier: Programming Language :: Python :: 3.4
Classifier: Programming Language :: Python :: 3.5
Requires-Dist: certifi
Requires-Dist: pycurl
